myFBGcommunication/__init__.py
myFBGcommunication/myFBGcommunication.py
myFBGcommunication/params.ini
myfbgcommunication-1.1.4.dist-info/METADATA
myfbgcommunication-1.1.4.dist-info/WHEEL
myfbgcommunication-1.1.4.dist-info/top_level.txt
myfbgcommunication-1.1.4.dist-info/RECORD
