Metadata-Version: 2.1
Name: myfbgcommunication
Version: 1.1.4
Summary: For FBG sensor.
Author: Toshihiro Nishimura
Author-email: tnishimura@se.kanazawa-u.ac.jp
License: MIT
Requires-Dist: pyserial
Requires-Dist: scipy
Requires-Dist: pandas
Requires-Dist: matplotlib
